craftier/__init__.py
craftier/__main__.py
craftier/class_finder.py
craftier/cli.py
craftier/codemod.py
craftier/config.py
craftier/fs.py
craftier/function_parser.py
craftier/libcst_typing.py
craftier/matcher.py
craftier/matchers.py
craftier/parenthesize.py
craftier/performance.py
craftier/refactor.py
craftier/refactors/__init__.py
craftier/refactors/sample.py
craftier/transformer.py
craftier/utils.py
craftier-0.1.0.dist-info/entry_points.txt
craftier-0.1.0.dist-info/LICENSE
craftier-0.1.0.dist-info/WHEEL
craftier-0.1.0.dist-info/METADATA
craftier-0.1.0.dist-info/RECORD
