Metadata-Version: 2.1
Name: craftier
Version: 0.1.0
Summary: 
Home-page: https://github.com/sk-/craftier
License: MIT
Keywords: refactor,lint,codemod,idiom,anti-pattern
Author: Sebastian Kreft
Requires-Python: >=3.7,<4.0
Classifier: Development Status :: 2 - Pre-Alpha
Classifier: Environment :: Console
Classifier: Intended Audience :: Developers
Classifier: License :: OSI Approved :: MIT License
Classifier: Operating System :: OS Independent
Classifier: Programming Language :: Python :: 3
Classifier: Programming Language :: Python :: 3.7
Classifier: Programming Language :: Python :: 3.8
Classifier: Topic :: Software Development
Classifier: Topic :: Software Development :: Quality Assurance
Requires-Dist: click (>=7.1.2,<8.0.0)
Requires-Dist: click_pathlib (>=2020.3.13,<2021.0.0)
Requires-Dist: libcst (>=0.3.15,<0.4.0)
Requires-Dist: loguru (>=0.5.3,<0.6.0)
Requires-Dist: typing_extensions (>=3.7.4,<4.0.0)
Project-URL: Repository, https://github.com/sk-/craftier
